README.md
setup.py
ROCKPAPERSTEROIDS/__init__.py
ROCKPAPERSTEROIDS/python_code.py
ROCKPAPERSTEROIDS.egg-info/PKG-INFO
ROCKPAPERSTEROIDS.egg-info/SOURCES.txt
ROCKPAPERSTEROIDS.egg-info/dependency_links.txt
ROCKPAPERSTEROIDS.egg-info/not-zip-safe
ROCKPAPERSTEROIDS.egg-info/top_level.txt