Metadata-Version: 1.0
Name: ROCKPAPERSTEROIDS
Version: 0.2
Summary: an extended game of rock paper scissor 
Home-page: https://github.com/MUSSONT/ROCKPAPERSTEROIDS
Author: Thomas Musson
Author-email: UNKNOWN
License: UNKNOWN
Platform: UNKNOWN
